neoinfo_nbdev/__init__.py
neoinfo_nbdev/_modidx.py
neoinfo_nbdev/core.py
neoinfo_nbdev-0.0.3.dist-info/LICENSE
neoinfo_nbdev-0.0.3.dist-info/METADATA
neoinfo_nbdev-0.0.3.dist-info/WHEEL
neoinfo_nbdev-0.0.3.dist-info/entry_points.txt
neoinfo_nbdev-0.0.3.dist-info/top_level.txt
neoinfo_nbdev-0.0.3.dist-info/RECORD
